CHANGES.rst
CONTRIBUTORS.rst
DEVELOP.rst
LICENSE.GPL
LICENSE.rst
MANIFEST.in
README.rst
constraints.txt
constraints_plone43.txt
constraints_plone51.txt
constraints_plone52.txt
requirements.txt
setup.cfg
setup.py
docs/index.rst
src/redturtle/__init__.py
src/redturtle.exporter.base.egg-info/PKG-INFO
src/redturtle.exporter.base.egg-info/SOURCES.txt
src/redturtle.exporter.base.egg-info/dependency_links.txt
src/redturtle.exporter.base.egg-info/entry_points.txt
src/redturtle.exporter.base.egg-info/namespace_packages.txt
src/redturtle.exporter.base.egg-info/not-zip-safe
src/redturtle.exporter.base.egg-info/requires.txt
src/redturtle.exporter.base.egg-info/top_level.txt
src/redturtle/exporter/__init__.py
src/redturtle/exporter/base/__init__.py
src/redturtle/exporter/base/configure.zcml
src/redturtle/exporter/base/interfaces.py
src/redturtle/exporter/base/setuphandlers.py
src/redturtle/exporter/base/testing.py
src/redturtle/exporter/base/adapters/__init__.py
src/redturtle/exporter/base/adapters/collective_geo.py
src/redturtle/exporter/base/adapters/configure.zcml
src/redturtle/exporter/base/adapters/discussions.py
src/redturtle/exporter/base/adapters/parents_types.py
src/redturtle/exporter/base/adapters/private_hierarchy.py
src/redturtle/exporter/base/adapters/solr.py
src/redturtle/exporter/base/browser/__init__.py
src/redturtle/exporter/base/browser/archetypes.zcml
src/redturtle/exporter/base/browser/configure.zcml
src/redturtle/exporter/base/browser/jsonify.py
src/redturtle/exporter/base/browser/users_and_groups.py
src/redturtle/exporter/base/browser/wrapper.py
src/redturtle/exporter/base/browser/migration/__init__.py
src/redturtle/exporter/base/browser/migration/topics.py
src/redturtle/exporter/base/example_files/example.pdf
src/redturtle/exporter/base/example_files/plone.png
src/redturtle/exporter/base/locales/redturtle.exporter.base.pot
src/redturtle/exporter/base/locales/update.sh
src/redturtle/exporter/base/profiles/default/metadata.xml
src/redturtle/exporter/base/tests/__init__.py
src/redturtle/exporter/base/tests/test_catalog_exporter_view.py
src/redturtle/exporter/base/tests/test_export_users_and_groups.py
src/redturtle/exporter/base/tests/test_wrapper.py