Metadata-Version: 2.1
Name: redturtle.exporter.base
Version: 1.2.3
Summary: Json exporter base for Plone
Home-page: https://pypi.python.org/pypi/redturtle.exporter.base
Author: RedTurtle Technology
Author-email: sviluppoplone@redturtle.it
License: GPL version 2
Keywords: Python Plone
Platform: UNKNOWN
Classifier: Environment :: Web Environment
Classifier: Framework :: Plone
Classifier: Framework :: Plone :: 4.3
Classifier: Framework :: Plone :: 5.1
Classifier: Programming Language :: Python
Classifier: Programming Language :: Python :: 2.7
Classifier: Operating System :: OS Independent
Classifier: License :: OSI Approved :: GNU General Public License v2 (GPLv2)
Provides-Extra: test
